JiqiZhixin2019GaofenJiaochengJingyanFenxiangShenduHaowenFix1/README.md
JiqiZhixin2019GaofenJiaochengJingyanFenxiangShenduHaowenFix1/__init__.py
JiqiZhixin2019GaofenJiaochengJingyanFenxiangShenduHaowenFix1/__main__.py
JiqiZhixin2019GaofenJiaochengJingyanFenxiangShenduHaowenFix1/file.epub
JiqiZhixin2019GaofenJiaochengJingyanFenxiangShenduHaowenFix1/index.html
JiqiZhixin2019GaofenJiaochengJingyanFenxiangShenduHaowenFix1/css/__init__.py
JiqiZhixin2019GaofenJiaochengJingyanFenxiangShenduHaowenFix1/css/annotations.css
JiqiZhixin2019GaofenJiaochengJingyanFenxiangShenduHaowenFix1/css/main.css
JiqiZhixin2019GaofenJiaochengJingyanFenxiangShenduHaowenFix1/css/normalize.css
JiqiZhixin2019GaofenJiaochengJingyanFenxiangShenduHaowenFix1/css/popup.css
JiqiZhixin2019GaofenJiaochengJingyanFenxiangShenduHaowenFix1/font/__init__.py
JiqiZhixin2019GaofenJiaochengJingyanFenxiangShenduHaowenFix1/font/fontello.eot
JiqiZhixin2019GaofenJiaochengJingyanFenxiangShenduHaowenFix1/font/fontello.svg
JiqiZhixin2019GaofenJiaochengJingyanFenxiangShenduHaowenFix1/font/fontello.ttf
JiqiZhixin2019GaofenJiaochengJingyanFenxiangShenduHaowenFix1/font/fontello.woff
JiqiZhixin2019GaofenJiaochengJingyanFenxiangShenduHaowenFix1/img/__init__.py
JiqiZhixin2019GaofenJiaochengJingyanFenxiangShenduHaowenFix1/img/annotator-glyph-sprite.png
JiqiZhixin2019GaofenJiaochengJingyanFenxiangShenduHaowenFix1/img/annotator-icon-sprite.png
JiqiZhixin2019GaofenJiaochengJingyanFenxiangShenduHaowenFix1/img/apple-touch-icon.png
JiqiZhixin2019GaofenJiaochengJingyanFenxiangShenduHaowenFix1/img/cancelfullscreen.png
JiqiZhixin2019GaofenJiaochengJingyanFenxiangShenduHaowenFix1/img/close.png
JiqiZhixin2019GaofenJiaochengJingyanFenxiangShenduHaowenFix1/img/fullscreen.png
JiqiZhixin2019GaofenJiaochengJingyanFenxiangShenduHaowenFix1/img/loader.gif
JiqiZhixin2019GaofenJiaochengJingyanFenxiangShenduHaowenFix1/img/menu-icon.png
JiqiZhixin2019GaofenJiaochengJingyanFenxiangShenduHaowenFix1/img/save.png
jiqi_zhixin_2019_gaofen_jiaocheng_jingyan_fenxiang_shendu_haowen_fix1-2025.3.24.0.dist-info/METADATA
jiqi_zhixin_2019_gaofen_jiaocheng_jingyan_fenxiang_shendu_haowen_fix1-2025.3.24.0.dist-info/WHEEL
jiqi_zhixin_2019_gaofen_jiaocheng_jingyan_fenxiang_shendu_haowen_fix1-2025.3.24.0.dist-info/entry_points.txt
jiqi_zhixin_2019_gaofen_jiaocheng_jingyan_fenxiang_shendu_haowen_fix1-2025.3.24.0.dist-info/top_level.txt
jiqi_zhixin_2019_gaofen_jiaocheng_jingyan_fenxiang_shendu_haowen_fix1-2025.3.24.0.dist-info/RECORD
