Metadata-Version: 2.1
Name: jiqi-zhixin-2019-gaofen-jiaocheng-jingyan-fenxiang-shendu-haowen-fix1
Version: 2025.3.24.0
Summary: 机器之心 2019 高分教程：经验分享，「深度好文」
Home-page: https://github.com/apachecn/jiqi-zhixin-2019-gaofen-jiaocheng-jingyan-fenxiang-shendu-haowen-fix1
Author: ApacheCN
Author-email: apachecn@163.com
Classifier: Development Status :: 4 - Beta
Classifier: Environment :: Console
Classifier: Intended Audience :: Developers
Classifier: Intended Audience :: End Users/Desktop
Classifier: License :: Other/Proprietary License
Classifier: Natural Language :: Chinese (Simplified)
Classifier: Natural Language :: English
Classifier: Operating System :: OS Independent
Classifier: Programming Language :: Python :: 3
Classifier: Programming Language :: Python :: 3 :: Only
Classifier: Programming Language :: Python :: 3.6
Classifier: Programming Language :: Python :: 3.7
Classifier: Topic :: Text Processing :: Markup :: Markdown
Classifier: Topic :: Text Processing :: Markup :: HTML
Classifier: Topic :: Internet :: WWW/HTTP
Classifier: Topic :: Software Development :: Documentation
Classifier: Topic :: Documentation
Requires-Python: >=3.6
